PythonShenduXuexiJiagouShiyongZhinanChuyiFix1/README.md
PythonShenduXuexiJiagouShiyongZhinanChuyiFix1/__init__.py
PythonShenduXuexiJiagouShiyongZhinanChuyiFix1/__main__.py
PythonShenduXuexiJiagouShiyongZhinanChuyiFix1/file.epub
PythonShenduXuexiJiagouShiyongZhinanChuyiFix1/index.html
PythonShenduXuexiJiagouShiyongZhinanChuyiFix1/css/__init__.py
PythonShenduXuexiJiagouShiyongZhinanChuyiFix1/css/annotations.css
PythonShenduXuexiJiagouShiyongZhinanChuyiFix1/css/main.css
PythonShenduXuexiJiagouShiyongZhinanChuyiFix1/css/normalize.css
PythonShenduXuexiJiagouShiyongZhinanChuyiFix1/css/popup.css
PythonShenduXuexiJiagouShiyongZhinanChuyiFix1/font/__init__.py
PythonShenduXuexiJiagouShiyongZhinanChuyiFix1/font/fontello.eot
PythonShenduXuexiJiagouShiyongZhinanChuyiFix1/font/fontello.svg
PythonShenduXuexiJiagouShiyongZhinanChuyiFix1/font/fontello.ttf
PythonShenduXuexiJiagouShiyongZhinanChuyiFix1/font/fontello.woff
PythonShenduXuexiJiagouShiyongZhinanChuyiFix1/img/__init__.py
PythonShenduXuexiJiagouShiyongZhinanChuyiFix1/img/annotator-glyph-sprite.png
PythonShenduXuexiJiagouShiyongZhinanChuyiFix1/img/annotator-icon-sprite.png
PythonShenduXuexiJiagouShiyongZhinanChuyiFix1/img/apple-touch-icon.png
PythonShenduXuexiJiagouShiyongZhinanChuyiFix1/img/cancelfullscreen.png
PythonShenduXuexiJiagouShiyongZhinanChuyiFix1/img/close.png
PythonShenduXuexiJiagouShiyongZhinanChuyiFix1/img/fullscreen.png
PythonShenduXuexiJiagouShiyongZhinanChuyiFix1/img/loader.gif
PythonShenduXuexiJiagouShiyongZhinanChuyiFix1/img/menu-icon.png
PythonShenduXuexiJiagouShiyongZhinanChuyiFix1/img/save.png
PythonShenduXuexiJiagouShiyongZhinanChuyiFix1/img/saved.png
PythonShenduXuexiJiagouShiyongZhinanChuyiFix1/img/settings-s.png
PythonShenduXuexiJiagouShiyongZhinanChuyiFix1/img/settings.png
PythonShenduXuexiJiagouShiyongZhinanChuyiFix1/img/star.png
PythonShenduXuexiJiagouShiyongZhinanChuyiFix1/js/__init__.py
PythonShenduXuexiJiagouShiyongZhinanChuyiFix1/js/epub.js
python_shendu_xuexi_jiagou_shiyong_zhinan_chuyi_fix1-2025.3.25.1.dist-info/METADATA
python_shendu_xuexi_jiagou_shiyong_zhinan_chuyi_fix1-2025.3.25.1.dist-info/WHEEL
python_shendu_xuexi_jiagou_shiyong_zhinan_chuyi_fix1-2025.3.25.1.dist-info/entry_points.txt
python_shendu_xuexi_jiagou_shiyong_zhinan_chuyi_fix1-2025.3.25.1.dist-info/top_level.txt
python_shendu_xuexi_jiagou_shiyong_zhinan_chuyi_fix1-2025.3.25.1.dist-info/RECORD
